tt_wizard_core.py
tt_wizard_core-1.0.0.dist-info/LICENSE
tt_wizard_core-1.0.0.dist-info/METADATA
tt_wizard_core-1.0.0.dist-info/WHEEL
tt_wizard_core-1.0.0.dist-info/top_level.txt
tt_wizard_core-1.0.0.dist-info/RECORD
