Metadata-Version: 2.1
Name: tt-wizard-core
Version: 1.0.0
Summary: Tool to download and manage gme-files. Core of TT_WIZARD.
Home-page: https://github.com/BumblebeeMan/tt_wizard_core
Author: BumblebeeMan (Dennis Schweer)
Author-email: dennis@bumblebeeman.engineer
Keywords: TipToi,TipTio,tip,toi,tio
Classifier: Development Status :: 4 - Beta
Classifier: License :: OSI Approved :: GNU General Public License v3 (GPLv3)
Classifier: Operating System :: OS Independent
Classifier: Programming Language :: Python :: 3
Classifier: Programming Language :: Python :: 3 :: Only
Classifier: Programming Language :: Python :: 3.7
Classifier: Programming Language :: Python :: 3.8
Classifier: Programming Language :: Python :: 3.9
Classifier: Programming Language :: Python :: 3.10
Classifier: Programming Language :: Python :: 3.11
Classifier: Topic :: Multimedia
Classifier: Topic :: Multimedia :: Sound/Audio
Requires-Python: >=3.7
License-File: LICENSE
Requires-Dist: requests >=2.30.0
Requires-Dist: psutil >=5.9.0
